README.md
setup.cfg
setup.py
shovel/__init__.py
shovel/args.py
shovel/help.py
shovel/parser.py
shovel/runner.py
shovel/tasks.py
shovel.egg-info/PKG-INFO
shovel.egg-info/SOURCES.txt
shovel.egg-info/dependency_links.txt
shovel.egg-info/entry_points.txt
shovel.egg-info/top_level.txt
test/test_args.py
test/test_help.py
test/test_parse.py
test/test_run.py
test/test_task.py