Metadata-Version: 1.1
Name: shovel
Version: 0.4.0
Summary: Not Rake, but Shovel
Home-page: http://github.com/seomoz/shovel
Author: Dan Lecocq
Author-email: dan@moz.com
License: MIT License
Keywords: tasks,shovel,rake
Platform: UNKNOWN
Classifier: License :: OSI Approved :: MIT License
Classifier: Programming Language :: Python
Classifier: Intended Audience :: Developers
Classifier: Operating System :: OS Independent
